tygle_drive/__init__.py
tygle_drive/drive.py
tygle_drive/rest/__init__.py
tygle_drive/rest/files.py
tygle_drive/types/__init__.py
tygle_drive/types/enums/__init__.py
tygle_drive/types/enums/files/__init__.py
tygle_drive/types/enums/files/any_mime_type.py
tygle_drive/types/enums/files/export_mime_type.py
tygle_drive/types/enums/files/google_mime_type.py
tygle_drive/types/enums/files/include_permissions_for_view.py
tygle_drive/types/enums/files/space.py
tygle_drive/types/enums/permissions/__init__.py
tygle_drive/types/enums/permissions/display_name.py
tygle_drive/types/enums/permissions/permission_details/__init__.py
tygle_drive/types/enums/permissions/permission_details/permission_type.py
tygle_drive/types/enums/permissions/permission_details/role.py
tygle_drive/types/enums/permissions/role.py
tygle_drive/types/enums/permissions/type.py
tygle_drive/types/resources/__init__.py
tygle_drive/types/resources/files/__init__.py
tygle_drive/types/resources/files/capabilities.py
tygle_drive/types/resources/files/content_hints.py
tygle_drive/types/resources/files/content_restriction.py
tygle_drive/types/resources/files/file.py
tygle_drive/types/resources/files/image_media_metadata.py
tygle_drive/types/resources/files/link_share_metadata.py
tygle_drive/types/resources/files/shortcut_details.py
tygle_drive/types/resources/files/user.py
tygle_drive/types/resources/files/video_media_metadata.py
tygle_drive/types/resources/permissions/__init__.py
tygle_drive/types/resources/permissions/permission.py
tygle_drive/types/resources/permissions/permission_details.py
tygle_drive/types/responses/__init__.py
tygle_drive/types/responses/files/__init__.py
tygle_drive/types/responses/files/list.py
tygle_drive-0.1.6.dist-info/WHEEL
tygle_drive-0.1.6.dist-info/METADATA
tygle_drive-0.1.6.dist-info/RECORD
